BlueLeader-0.32.6.dist-info/DESCRIPTION.rst
BlueLeader-0.32.6.dist-info/METADATA
BlueLeader-0.32.6.dist-info/RECORD
BlueLeader-0.32.6.dist-info/WHEEL
BlueLeader-0.32.6.dist-info/entry_points.txt
BlueLeader-0.32.6.dist-info/metadata.json
BlueLeader-0.32.6.dist-info/top_level.txt
blueleader/__init__.py
blueleader/deploy.py
blueleader/frontend_deploy.py
blueleader/s3.py
blueleader/webpack.py
